docs/source/conf.py
examples/__init__.py
examples/classification/CIFAR.py
examples/classification/Evaluation.py
examples/classification/__init__.py
examples/classification/utils.py
examples/detection/Calibration.py
examples/detection/Evaluation.py
examples/detection/Features.py
examples/detection/Helper.py
examples/detection/__init__.py
examples/regression/__init__.py
examples/regression/artificial/__init__.py
examples/regression/artificial/data.py
examples/regression/artificial/main.py
examples/regression/artificial/visualize.py
examples/regression/multivariate/__init__.py
examples/regression/multivariate/data.py
examples/regression/multivariate/main.py
examples/regression/multivariate/visualize.py
netcal/AbstractCalibration.py
netcal/Context.py
netcal/Decorator.py
netcal/Helper.py
netcal/Stats.py
netcal/__init__.py
netcal/binning/BBQ.py
netcal/binning/ENIR.py
netcal/binning/HistogramBinning.py
netcal/binning/IsotonicRegression.py
netcal/binning/NearIsotonicRegression.py
netcal/binning/__init__.py
netcal/metrics/Miscalibration.py
netcal/metrics/__init__.py
netcal/metrics/confidence/ACE.py
netcal/metrics/confidence/ECE.py
netcal/metrics/confidence/MCE.py
netcal/metrics/confidence/MMCE.py
netcal/metrics/confidence/__init__.py
netcal/metrics/regression/ENCE.py
netcal/metrics/regression/NLL.py
netcal/metrics/regression/PICP.py
netcal/metrics/regression/QCE.py
netcal/metrics/regression/QuantileLoss.py
netcal/metrics/regression/UCE.py
netcal/metrics/regression/__init__.py
netcal/presentation/ReliabilityDiagram.py
netcal/presentation/ReliabilityQCE.py
netcal/presentation/ReliabilityRegression.py
netcal/presentation/__init__.py
netcal/regression/IsotonicRegression.py
netcal/regression/VarianceScaling.py
netcal/regression/__init__.py
netcal/regression/gp/AbstractGP.py
netcal/regression/gp/GPBeta.py
netcal/regression/gp/GPCauchy.py
netcal/regression/gp/GPNormal.py
netcal/regression/gp/__init__.py
netcal/regression/gp/kernel/GaussianRBFKernel.py
netcal-1.3.6.dist-info/LICENSE.txt
netcal-1.3.6.dist-info/METADATA
netcal-1.3.6.dist-info/WHEEL
netcal-1.3.6.dist-info/top_level.txt
netcal-1.3.6.dist-info/RECORD
