Metadata-Version: 2.1
Name: netcal
Version: 1.3.6
Summary: The net:cal calibration framework is a Python 3 library for measuring and mitigating miscalibration of uncertainty estimates, e.g., by a neural network.
Author: Fabian Küppers
Author-email: fabian.kueppers@efs-techhub.com
Maintainer: Fabian Küppers
Maintainer-email: fabian.kueppers@efs-techhub.com
License: Apache-2.0
Project-URL: Homepage, https://github.com/EFS-OpenSource/calibration-framework
Project-URL: Documentation, https://efs-opensource.github.io/calibration-framework
Keywords: netcal,calibration,uncertainty,neural,network,confidence,classification,object,detection,regression
Classifier: Programming Language :: Python :: 3
Classifier: License :: OSI Approved :: Apache Software License
Classifier: Operating System :: OS Independent
Classifier: Development Status :: 5 - Production/Stable
Classifier: Topic :: Scientific/Engineering :: Artificial Intelligence
Requires-Python: >=3.6
License-File: LICENSE.txt
Requires-Dist: numpy >=1.18
Requires-Dist: scipy >=1.4
Requires-Dist: matplotlib <3.8,>=3.3
Requires-Dist: scikit-learn >=0.24
Requires-Dist: torch >=1.9
Requires-Dist: torchvision >=0.10.0
Requires-Dist: tqdm >=4.40
Requires-Dist: pyro-ppl >=1.8
Requires-Dist: tikzplotlib ==0.9.8
Requires-Dist: tensorboard >=2.2
Requires-Dist: gpytorch >=1.5.1
